skill_support_helper/LICENSE.md
skill_support_helper/README.md
skill_support_helper/__init__.py
skill_support_helper/skill.json
skill_support_helper/version.py
skill_support_helper/locale/de-de/dialog/ask_description.dialog
skill_support_helper/locale/de-de/dialog/cancelled.dialog
skill_support_helper/locale/de-de/dialog/complete.dialog
skill_support_helper/locale/de-de/dialog/confirm_support.dialog
skill_support_helper/locale/de-de/dialog/email_signature.dialog
skill_support_helper/locale/de-de/dialog/email_title.dialog
skill_support_helper/locale/de-de/dialog/one_moment.dialog
skill_support_helper/locale/de-de/dialog/support.dialog
skill_support_helper/locale/de-de/dialog/yes.list
skill_support_helper/locale/de-de/vocab/contact_support.intent
skill_support_helper/locale/en-us/dialog/ask_description.dialog
skill_support_helper/locale/en-us/dialog/cancelled.dialog
skill_support_helper/locale/en-us/dialog/complete.dialog
skill_support_helper/locale/en-us/dialog/confirm_support.dialog
skill_support_helper/locale/en-us/dialog/email_error.dialog
skill_support_helper/locale/en-us/dialog/email_intro.dialog
skill_support_helper/locale/en-us/dialog/email_signature.dialog
skill_support_helper/locale/en-us/dialog/email_title.dialog
skill_support_helper/locale/en-us/dialog/no_email.dialog
skill_support_helper/locale/en-us/dialog/one_moment.dialog
skill_support_helper/locale/en-us/dialog/support.dialog
skill_support_helper/locale/en-us/intent/contact_support.intent
skill_support_helper/neon_skill_support_helper.egg-info/PKG-INFO
skill_support_helper/neon_skill_support_helper.egg-info/SOURCES.txt
skill_support_helper/neon_skill_support_helper.egg-info/dependency_links.txt
skill_support_helper/neon_skill_support_helper.egg-info/entry_points.txt
skill_support_helper/neon_skill_support_helper.egg-info/requires.txt
skill_support_helper/neon_skill_support_helper.egg-info/top_level.txt
skill_support_helper/test/test_skill.py
neon_skill_support_helper-1.2.4.dist-info/LICENSE.md
neon_skill_support_helper-1.2.4.dist-info/METADATA
neon_skill_support_helper-1.2.4.dist-info/WHEEL
neon_skill_support_helper-1.2.4.dist-info/entry_points.txt
neon_skill_support_helper-1.2.4.dist-info/top_level.txt
neon_skill_support_helper-1.2.4.dist-info/RECORD
